django_simple_social/__init__.py
django_simple_social/backends.py
django_simple_social/options.py
django_simple_social-0.1.10.dist-info/DESCRIPTION.rst
django_simple_social-0.1.10.dist-info/METADATA
django_simple_social-0.1.10.dist-info/pydist.json
django_simple_social-0.1.10.dist-info/RECORD
django_simple_social-0.1.10.dist-info/top_level.txt
django_simple_social-0.1.10.dist-info/WHEEL
