Metadata-Version: 2.0
Name: django-simple-social
Version: 0.1.10
Summary: A generic system for interacting with remote APIs that need to create Django socials.
Home-page: https://github.com/mattsnider/Django-Simple-Social
Author: Matt Snider
Author-email: admin@mattsnider.com
License: MIT
Keywords: simple,social,linkedin,facebook,twitter
Platform: UNKNOWN
Classifier: Programming Language :: Python
Classifier: License :: OSI Approved :: MIT License
Classifier: Operating System :: OS Independent
Classifier: Development Status :: 3 - Alpha
Classifier: Environment :: Web Environment
Classifier: Intended Audience :: Developers
Classifier: Topic :: Software Development :: Libraries :: Python Modules
Requires-Dist: django (>=1.3)
Requires-Dist: django-social-user
Requires-Dist: facebook-sdk
Requires-Dist: linkedin-api-json-client
Requires-Dist: twython
